ndapfirstuseauthenticator/__init__.py
ndapfirstuseauthenticator/_version.py
ndapfirstuseauthenticator/firstuseauthenticator.py
ndapfirstuseauthenticator/templates/__init__.py
ndapfirstuseauthenticator/templates/reset.html
jupyterhub_ndapfirstuseauthenticator-0.14.2.dev0.dist-info/LICENSE
jupyterhub_ndapfirstuseauthenticator-0.14.2.dev0.dist-info/METADATA
jupyterhub_ndapfirstuseauthenticator-0.14.2.dev0.dist-info/WHEEL
jupyterhub_ndapfirstuseauthenticator-0.14.2.dev0.dist-info/top_level.txt
jupyterhub_ndapfirstuseauthenticator-0.14.2.dev0.dist-info/RECORD
