Metadata-Version: 2.1
Name: jupyterhub-ndapfirstuseauthenticator
Version: 0.14.2.dev0
Summary: NDAP Token Authenticator and JupyterHub Authenticator that lets users set passwords on first use
Home-page: https://github.com/manu625/jupyterhub-ndapauthenticator
Author: manu625
Author-email: im.manu625@gmail.com
License: 3 Clause BSD
Platform: UNKNOWN
Requires-Dist: bcrypt
Requires-Dist: jupyterhub (>=0.8)
Requires-Dist: requests
